{
	"mapwidth":"1920",
	"mapheight":"1080",
	"categories":[
	{
	  "id": "HRE0",
      "title": "Etches Park Site",
      "color": "#2d2d2d",
      "show": "false"
	 },
	{
	 "id": "HRE1",
      "title": "North Shed",
      "color": "#2d2d2d",
      "show": "false"
	 },
	{
	"id": "HRE2",
      "title": "4 Shed",
      "color": "#2d2d2d",
      "show": "false"
	 },
	{
	"id": "HRE3",
      "title": "Assembly Points",
      "color": "#2d2d2d",
      "show": "true"
	 }
	
	],
	"levels":[
		
		{
			"id":"Site",
			"title":"Etches Park Site",
			"map":"maps/etches_source7.svg",
			"minimap": "maps/etches_mini.jpg",
			"locations":[
				{
					"id": "northshed",
					"title": "North Shed",
					"category": "HRE0",
					"description": "TBC",
					"pin": "hidden",
					"about":"",
					"fill": "#FF0026",
					"link": "?location=First_loc",
					"image": "images/northshed.jpg",
					"thumbnail": "images/northshed.jpg",
					"zoom":"2",
					"x": "0.3400",
					"y": "0.4750"
				},
				
				{
					"id": "shed",
					"title": "4 Shed",
					"category": "HRE0",
					"description": "TBC",
					"pin": "hidden",
					"about":"",
					"fill": "#FF0026",
					"link": "?location=Second_loc",
					"image": "images/shed.jpg",
					"thumbnail": "images/shed.jpg",
					"zoom":"2",
					"x": "0.2000",
					"y": "0.2900"
				},

				{
					"id": "Aassembly",
					"title": "Evac point 1",
					"category": "HRE3",
					"description": "Located near South entrance at Deadmans Lane.",
					"pin": "hidden",
					"fill": "#FF0026",
					"image": "images/ep_ass_A.jpg",
					"thumbnail": "images/ep_ass_A.jpg",
					"zoom":"2",
					"x": "0.9550",
					"y": "0.8250"
				},
				
				{
					"id": "Bassembly",
					"title": "Evac point 2",
					"category": "HRE3",
					"description": "Located near the Brunel Parkway entrance.",
					"pin": "hidden",
					"fill": "#FF0026",
					"image": "images/ep_ass_B.jpg",
					"thumbnail": "images/ep_ass_B.jpg",
					"zoom":"2",
					"x": "0.4800",
					"y": "0.4800"
				},
				
				{
					"id": "Cassembly",
					"title": "Evac point 3",
					"category": "HRE3",
					"description": "Located in the car park between North Shed and 4 Shed",
					"pin": "hidden",
					"fill": "#FF0026",
					"image": "images/ep_ass_C.jpg",
					"thumbnail": "images/ep_ass_C.jpg",
					"zoom":"2",
					"x": "0.2700",
					"y": "0.4020"
				}

			]
		},

		
		{
			"id":"Northshed",
			"title":"North Shed",
			"map":"maps/EP_North_Shed7.svg",
			"minimap": "maps/ep_northshed_mini.jpg",
			"locations":[
				{
					"id": "First_loc",
					"title": "North Shed Floorplan",
					"category": "HRE1",
					"description": "",
					"pin": "hidden",
					"show": "false",
					"about":"",
					"fill": "#FF0026",
					"zoom":"0",
					"x": "10",
					"y": "0"
				}
				
				
			]
		},
		{
			"id":"Shed",
			"title":"4 Shed",
			"map":"maps/EP_4_Shed-01.svg",
			"minimap": "maps/ep_4shed_mini.jpg",
			"locations":[
			{
				"id": "Second_loc",
				"title": "4 Shed Floorplan",
				"category": "HRE2",
				"description": "",
				"pin": "hidden",
				"show": "false",
				"about":"",
				"fill": "#FF0026",
				"zoom":"0",
				"x": "10",
				"y": "0"
				}
				
				
			]
	
		}
		
		
		
		
		
		
		
	]
}
